kumisms/__init__.py
kumisms-0.1.4.dist-info/LICENSE
kumisms-0.1.4.dist-info/METADATA
kumisms-0.1.4.dist-info/WHEEL
kumisms-0.1.4.dist-info/top_level.txt
kumisms-0.1.4.dist-info/RECORD
