Metadata-Version: 2.1
Name: kumisms
Version: 0.1.4
Summary: Class to interact with KumiSMS
Home-page: https://kumig.it/kumisystems/pykumisms
Author: Kumi Systems e.U.
Author-email: support@kumi.systems
License: BSD-2-Clause
Platform: UNKNOWN
Classifier: Environment :: Web Environment
Classifier: Intended Audience :: Developers
Classifier: License :: OSI Approved :: BSD License
Classifier: Operating System :: OS Independent
Classifier: Programming Language :: Python
Classifier: Programming Language :: Python :: 3
Classifier: Programming Language :: Python :: 3 :: Only
Classifier: Programming Language :: Python :: 3.6
Classifier: Programming Language :: Python :: 3.7
Classifier: Programming Language :: Python :: 3.8
